iconvert
