Metadata-Version: 2.1
Name: iconvert
Version: 1.0.8
Summary: Convert images to .ico format for icon use in Windows
Home-page: https://github.com/nrdrch/iconvert
Author: nrdrch
Keywords: image convert ico windows icon
